{
  "type": "Program",
  "start": 0,
  "end": 216,
  "loc": {
    "start": {
      "line": 1,
      "column": 0
    },
    "end": {
      "line": 17,
      "column": 0
    }
  },
  "sourceType": "module",
  "body": [
    {
      "type": "ImportDeclaration",
      "start": 45,
      "end": 103,
      "loc": {
        "start": {
          "line": 5,
          "column": 0
        },
        "end": {
          "line": 5,
          "column": 58
        }
      },
      "specifiers": [
        {
          "type": "ImportDefaultSpecifier",
          "start": 52,
          "end": 67,
          "loc": {
            "start": {
              "line": 5,
              "column": 7
            },
            "end": {
              "line": 5,
              "column": 22
            }
          },
          "local": {
            "type": "Identifier",
            "start": 52,
            "end": 67,
            "loc": {
              "start": {
                "line": 5,
                "column": 7
              },
              "end": {
                "line": 5,
                "column": 22
              }
            },
            "name": "_CUSTOM_MD_Data",
            "leadingComments": null
          },
          "leadingComments": null
        }
      ],
      "importKind": "value",
      "source": {
        "type": "Literal",
        "start": 73,
        "end": 102,
        "loc": {
          "start": {
            "line": 5,
            "column": 28
          },
          "end": {
            "line": 5,
            "column": 57
          }
        },
        "value": "json!../json/CUSTOM_MD.json",
        "rawValue": "json!../json/CUSTOM_MD.json",
        "raw": "'json!../json/CUSTOM_MD.json'"
      },
      "leadingComments": [
        {
          "type": "Block",
          "value": "*\n * Mocking client-server processing\n ",
          "start": 0,
          "end": 43,
          "loc": {
            "start": {
              "line": 1,
              "column": 0
            },
            "end": {
              "line": 3,
              "column": 3
            }
          },
          "range": [
            0,
            43
          ]
        }
      ]
    },
    {
      "type": "VariableDeclaration",
      "start": 105,
      "end": 124,
      "loc": {
        "start": {
          "line": 7,
          "column": 0
        },
        "end": {
          "line": 7,
          "column": 19
        }
      },
      "declarations": [
        {
          "type": "VariableDeclarator",
          "start": 111,
          "end": 124,
          "loc": {
            "start": {
              "line": 7,
              "column": 6
            },
            "end": {
              "line": 7,
              "column": 19
            }
          },
          "id": {
            "type": "Identifier",
            "start": 111,
            "end": 118,
            "loc": {
              "start": {
                "line": 7,
                "column": 6
              },
              "end": {
                "line": 7,
                "column": 13
              }
            },
            "name": "TIMEOUT"
          },
          "init": {
            "type": "Literal",
            "start": 121,
            "end": 124,
            "loc": {
              "start": {
                "line": 7,
                "column": 16
              },
              "end": {
                "line": 7,
                "column": 19
              }
            },
            "value": 100,
            "rawValue": 100,
            "raw": "100"
          }
        }
      ],
      "kind": "const"
    },
    {
      "type": "ExportDefaultDeclaration",
      "start": 126,
      "end": 215,
      "loc": {
        "start": {
          "line": 9,
          "column": 0
        },
        "end": {
          "line": 16,
          "column": 1
        }
      },
      "declaration": {
        "type": "ObjectExpression",
        "start": 141,
        "end": 215,
        "loc": {
          "start": {
            "line": 9,
            "column": 15
          },
          "end": {
            "line": 16,
            "column": 1
          }
        },
        "properties": [
          {
            "type": "Property",
            "start": 147,
            "end": 212,
            "loc": {
              "start": {
                "line": 12,
                "column": 2
              },
              "end": {
                "line": 14,
                "column": 3
              }
            },
            "method": true,
            "shorthand": false,
            "computed": false,
            "key": {
              "type": "Identifier",
              "start": 147,
              "end": 165,
              "loc": {
                "start": {
                  "line": 12,
                  "column": 2
                },
                "end": {
                  "line": 12,
                  "column": 20
                }
              },
              "name": "get_CUSTOM_MD_Data"
            },
            "kind": "init",
            "value": {
              "type": "FunctionExpression",
              "start": 165,
              "end": 212,
              "loc": {
                "start": {
                  "line": 12,
                  "column": 20
                },
                "end": {
                  "line": 14,
                  "column": 3
                }
              },
              "id": null,
              "generator": false,
              "expression": false,
              "async": false,
              "params": [
                {
                  "type": "Identifier",
                  "start": 166,
                  "end": 168,
                  "loc": {
                    "start": {
                      "line": 12,
                      "column": 21
                    },
                    "end": {
                      "line": 12,
                      "column": 23
                    }
                  },
                  "name": "cb"
                },
                {
                  "type": "Identifier",
                  "start": 170,
                  "end": 177,
                  "loc": {
                    "start": {
                      "line": 12,
                      "column": 25
                    },
                    "end": {
                      "line": 12,
                      "column": 32
                    }
                  },
                  "name": "timeout"
                }
              ],
              "body": {
                "type": "BlockStatement",
                "start": 179,
                "end": 212,
                "loc": {
                  "start": {
                    "line": 12,
                    "column": 34
                  },
                  "end": {
                    "line": 14,
                    "column": 3
                  }
                },
                "body": [
                  {
                    "type": "ReturnStatement",
                    "start": 185,
                    "end": 208,
                    "loc": {
                      "start": {
                        "line": 13,
                        "column": 4
                      },
                      "end": {
                        "line": 13,
                        "column": 27
                      }
                    },
                    "argument": {
                      "type": "Identifier",
                      "start": 192,
                      "end": 207,
                      "loc": {
                        "start": {
                          "line": 13,
                          "column": 11
                        },
                        "end": {
                          "line": 13,
                          "column": 26
                        }
                      },
                      "name": "_CUSTOM_MD_Data"
                    }
                  }
                ]
              }
            }
          }
        ],
        "leadingComments": [],
        "trailingComments": []
      }
    }
  ]
}